overlan/__init__.py
overlan3-0.0.1.dist-info/LICENSE.txt
overlan3-0.0.1.dist-info/METADATA
overlan3-0.0.1.dist-info/WHEEL
overlan3-0.0.1.dist-info/entry_points.txt
overlan3-0.0.1.dist-info/top_level.txt
overlan3-0.0.1.dist-info/RECORD
