Metadata-Version: 2.1
Name: overlan3
Version: 0.0.1
Summary: Python Socket Tools
Home-page: https://github.com/YannBouyeron/overlan/
Author: Yann Bouyeron
Author-email: yann.bouyeron@hotmail.fr
License: GPL3
Project-URL: Source, https://github.com/YannBouyeron/overlan/
Classifier: Development Status :: 3 - Alpha
Classifier: Intended Audience :: Developers
Classifier: Topic :: Software Development :: Build Tools
Classifier: License :: OSI Approved :: GNU General Public License v3 or later (GPLv3+)
Classifier: Programming Language :: Python :: 3.6
Classifier: Programming Language :: Python :: 3.7
Classifier: Programming Language :: Python :: 3.8
Classifier: Programming Language :: Python :: 3.9
Classifier: Programming Language :: Python :: 3.10
Requires-Python: >=3.6
License-File: LICENSE.txt
Requires-Dist: pycryptodome
Requires-Dist: paramiko
